image_processing/__init__.py
image_processing/processing/__init__.py
image_processing/processing/combination.py
image_processing/processing/transformation.py
image_processing/sample_images/autumn_forest.jpg
image_processing/sample_images/green_forest.jpg
image_processing/sample_images/river_forest.jpg
image_processing/utils/__init__.py
image_processing/utils/io.py
image_processing/utils/plot.py
image_processing-0.0.1.dist-info/METADATA
image_processing-0.0.1.dist-info/WHEEL
image_processing-0.0.1.dist-info/top_level.txt
image_processing-0.0.1.dist-info/RECORD
