Metadata-Version: 2.1
Name: image-processing
Version: 0.0.1
Summary: Image processing package using skimage
Home-page: https://github.com/tiemi/image-processing-package
Author: Karina Tiemi
License: UNKNOWN
Platform: UNKNOWN
Requires-Python: >=3.5
Requires-Dist: scikit-image (>=0.16.1)
Requires-Dist: numpy
Requires-Dist: matplotlib
